quick_vcn/__init__.py
quick_vcn/cmd.py
quick_vcn-0.0.2.dist-info/LICENCE.md
quick_vcn-0.0.2.dist-info/METADATA
quick_vcn-0.0.2.dist-info/WHEEL
quick_vcn-0.0.2.dist-info/entry_points.txt
quick_vcn-0.0.2.dist-info/top_level.txt
quick_vcn-0.0.2.dist-info/RECORD
