Metadata-Version: 2.1
Name: quick-vcn
Version: 0.0.2
Summary: Set up an OCI VCN and components quickly
Home-page: UNKNOWN
Author: jan grant 
Author-email: quick-vcn@ioctl.org
License: Apache License 2.0
Platform: UNKNOWN
Requires-Dist: argcomplete
Requires-Dist: oci
